LICENSE
MANIFEST.in
README.md
setup.cfg
setup.py
lanms/__init__.py
lanms_nova.egg-info/PKG-INFO
lanms_nova.egg-info/SOURCES.txt
lanms_nova.egg-info/dependency_links.txt
lanms_nova.egg-info/not-zip-safe
lanms_nova.egg-info/requires.txt
lanms_nova.egg-info/top_level.txt
src/Makefile
src/lanmslib.cpp
src/lanmslib.h
src/include/clipper/clipper.cpp
src/include/clipper/clipper.h
src/include/pybind11/attr.h
src/include/pybind11/buffer_info.h
src/include/pybind11/cast.h
src/include/pybind11/chrono.h
src/include/pybind11/common.h
src/include/pybind11/complex.h
src/include/pybind11/eigen.h
src/include/pybind11/embed.h
src/include/pybind11/eval.h
src/include/pybind11/functional.h
src/include/pybind11/gil.h
src/include/pybind11/iostream.h
src/include/pybind11/numpy.h
src/include/pybind11/operators.h
src/include/pybind11/options.h
src/include/pybind11/pybind11.h
src/include/pybind11/pytypes.h
src/include/pybind11/stl.h
src/include/pybind11/stl_bind.h
src/include/pybind11/detail/class.h
src/include/pybind11/detail/common.h
src/include/pybind11/detail/descr.h
src/include/pybind11/detail/init.h
src/include/pybind11/detail/internals.h
src/include/pybind11/detail/type_caster_base.h
src/include/pybind11/detail/typeid.h
src/include/pybind11/eigen/matrix.h
src/include/pybind11/eigen/tensor.h
src/include/pybind11/stl/filesystem.h