Metadata-Version: 2.1
Name: lanms-nova
Version: 1.0.3
Summary: lanms-nova is a python binding for LANMS - Locality-Aware Non-Max Suppression
Home-page: https://github.com/AndranikSargsyan/lanms-nova
Author: Andranik Sargsyan
Author-email: and.sargsyab@yahoo.com
License: GPL
Keywords: NMS,LANMS
Platform: UNKNOWN
License-File: LICENSE
